duckgo/__init__.py
duckgo/types.py
duckgo-0.1.1.dist-info/LICENSE
duckgo-0.1.1.dist-info/WHEEL
duckgo-0.1.1.dist-info/METADATA
duckgo-0.1.1.dist-info/RECORD
