Metadata-Version: 2.1
Name: duckgo
Version: 0.1.1
Summary: Search DuckDuckGo for websites, images, etc.
License: MIT
Author: Wanasit T
Requires-Python: >=3.7,<4.0
Classifier: License :: OSI Approved :: MIT License
Classifier: Programming Language :: Python :: 3
Classifier: Programming Language :: Python :: 3.10
Classifier: Programming Language :: Python :: 3.7
Classifier: Programming Language :: Python :: 3.8
Classifier: Programming Language :: Python :: 3.9
Requires-Dist: requests (>=2.1,<3.0)
